autoclick/__init__.py
autoclick/auto.py
autoclick/click_class.py
autoclick/command.py
auto_click-0.0.11.dist-info/METADATA
auto_click-0.0.11.dist-info/WHEEL
auto_click-0.0.11.dist-info/entry_points.txt
auto_click-0.0.11.dist-info/top_level.txt
auto_click-0.0.11.dist-info/RECORD
