Metadata-Version: 2.1
Name: auto-click
Version: 0.0.11
Summary: Python Auto-Click Library.
Home-page: UNKNOWN
Author: Jung Ji-Hyo
Author-email: cord0318@gmail.com
License: UNKNOWN
Keywords: korea,autoclick,auto,jihyo,click,auto-click
Platform: UNKNOWN
Classifier: Programming Language :: Python :: 3
Classifier: License :: OSI Approved :: MIT License
Classifier: Operating System :: OS Independent
Requires-Python: >=3
Requires-Dist: click
Requires-Dist: pynput
